{
  "context-menu": {
    "atom-text-editor": [
      {
        "type": "separator"
      },
      {
        "label": "Activate TeSSLa2",
        "command": "tessla2:activate"
      },
      {
        "label": "Deactivate TeSSLa2",
        "command": "tessla2:deactivate"
      },
      {
        "type": "separator"
      }
    ],
    "#tessla-message-panel-wrapper": [
      {
        "label": "Copy",
        "command": "core:copy"
      }
    ]
  },
  "menu": [
    {
      "label": "Packages",
      "submenu": [
        {
          "label": "TeSSLa2",
          "submenu": [
            {
              "label": "Activate",
              "command": "tessla2:activate"
            },
            {
              "label": "Deactivate",
              "command": "tessla2:deactivate"
            },
            {
              "type": "separator"
            },
            {
              "label": "Build C code",
              "command": "tessla2:build-c-code"
            },
            {
              "label": "Create trace file",
              "command": "tessla2:create-trace"
            },
            {
              "label": "Run C code",
              "command": "tessla2:run-c-code"
            },
            {
              "label": "Build and Run C code",
              "command": "tessla2:build-and-run-c-code"
            },
            {
              "label": "Build and Run Project",
              "command": "tessla2:build-and-run-project"
            },
            {
              "label": "Run Project by Trace",
              "command": "tessla2:run-project-by-trace"
            },
            {
              "label": "Stop current process",
              "command": "tessla2:stop-current-process"
            },
            {
              "type": "separator"
            },
            {
              "label": "Set up split view",
              "command": "tessla2:set-up-split-view"
            },
            {
              "label": "Restore all view Components",
              "command": "tessla2:reset-view"
            }
          ]
        }
      ]
    }
  ]
}
